setup.py
bin/codic
codic/__init__.py
codic/api.py
codic/cli.py
codic/config.py
codic/executor.py
codic/formatter.py
codic.egg-info/PKG-INFO
codic.egg-info/SOURCES.txt
codic.egg-info/dependency_links.txt
codic.egg-info/requires.txt
codic.egg-info/top_level.txt