Metadata-Version: 1.0
Name: codic
Version: 0.1.2
Summary: Codic CLI
Home-page: https://github.com/tuvistavie/codic-cli
Author: Daniel Perez
Author-email: tuvistavie@gmail.com
License: UNKNOWN
Platform: UNKNOWN
